agent_relay/__init__.py
agent_relay/cloud.py
agent_relay/context.py
agent_relay/db.py
agent_relay/llm.py
agent_relay/runtime.py
agent_relay/schema.py
agent_relay/tooling.py
agent_relay_api-0.1.2.dist-info/licenses/LICENSE.txt
agent_relay_api-0.1.2.dist-info/METADATA
agent_relay_api-0.1.2.dist-info/WHEEL
agent_relay_api-0.1.2.dist-info/top_level.txt
agent_relay_api-0.1.2.dist-info/RECORD
