Metadata-Version: 2.4
Name: agent_relay_api
Version: 0.1.2
Summary: A small runtime to trace, replay and debug multi-tool AI agents.
Author-email: Tejas Yalamanchili <tyalaman03@gmail.com>
License: LICENSE
Project-URL: Homepage, https://github.com/YalmanchiliTejas/agentRelayWebsite
Project-URL: Source, https://github.com/YalmanchiliTejas/agentRelayWebsite
Project-URL: Issues, https://github.com/YalmanchiliTejas/agentRelayWebsite
Keywords: agents,tracing,observability,workflow,ai
Classifier: Programming Language :: Python
Classifier: Programming Language :: Python :: 3
Classifier: Programming Language :: Python :: 3 :: Only
Classifier: Programming Language :: Python :: 3.9
Classifier: Programming Language :: Python :: 3.10
Classifier: Programming Language :: Python :: 3.11
Classifier: License :: Other/Proprietary License
Classifier: Operating System :: OS Independent
Requires-Python: >=3.9
License-File: LICENSE.txt
Requires-Dist: requests>=2.28
Requires-Dist: SQLAlchemy>=2.0
Requires-Dist: typing-extensions>=4.0
Provides-Extra: dev
Requires-Dist: build>=1.0.0; extra == "dev"
Requires-Dist: twine>=5.0.0; extra == "dev"
Requires-Dist: pytest>=7.0.0; extra == "dev"
Dynamic: license-file
